README.rst
csvconvert.py
setup.py
csvconvert.egg-info/PKG-INFO
csvconvert.egg-info/SOURCES.txt
csvconvert.egg-info/dependency_links.txt
csvconvert.egg-info/entry_points.txt
csvconvert.egg-info/top_level.txt