Metadata-Version: 1.0
Name: csvconvert
Version: 0.1
Summary: A tool to convert between various csv variants
Home-page: UNKNOWN
Author: UNKNOWN
Author-email: szymon@pythonista.net
License: UNKNOWN
Platform: UNKNOWN
